textifiers/__init__.py
textifiers/util.py
textifiers-0.0.1.dist-info/LICENSE
textifiers-0.0.1.dist-info/METADATA
textifiers-0.0.1.dist-info/WHEEL
textifiers-0.0.1.dist-info/top_level.txt
textifiers-0.0.1.dist-info/RECORD
