Metadata-Version: 2.1
Name: textifiers
Version: 0.0.1
Summary: WIP
Home-page: https://github.com/yourusername/textifiers
Author: Your Name
Author-email: email@example.com
Classifier: Programming Language :: Python :: 3
Classifier: License :: OSI Approved :: MIT License
Classifier: Operating System :: OS Independent
Requires-Python: >=3.6
License-File: LICENSE
